tgzr/contextual_settings/__init__.py
tgzr/contextual_settings/_version.py
tgzr/contextual_settings/context_data.py
tgzr/contextual_settings/context_name.py
tgzr/contextual_settings/items.py
tgzr/contextual_settings/ops.py
tgzr/contextual_settings/demo/__init__.py
tgzr/contextual_settings/demo/__main__.py
tgzr/contextual_settings/demo/app.py
tgzr/contextual_settings/demo/config.py
tgzr/contextual_settings/demo/assets/sky_bg.jpg
tgzr/contextual_settings/demo/assets/tgzr_contextual_settings-logo.svg
tgzr/contextual_settings/demo/assets/tgzr_contextual_settings_icon.png
tgzr/contextual_settings/demo/assets/favicon/android-chrome-192x192.png
tgzr/contextual_settings/demo/assets/favicon/android-chrome-512x512.png
tgzr/contextual_settings/demo/assets/favicon/apple-touch-icon.png
tgzr/contextual_settings/demo/assets/favicon/favicon-16x16.png
tgzr/contextual_settings/demo/assets/favicon/favicon-32x32.png
tgzr/contextual_settings/demo/assets/favicon/favicon.ico
tgzr/contextual_settings/demo/assets/favicon/site.webmanifest
tgzr/contextual_settings/demo/components/__init__.py
tgzr/contextual_settings/demo/components/conf_explorer.py
tgzr/contextual_settings/demo/components/header.py
tgzr/contextual_settings/demo/components/left_drawer.py
tgzr/contextual_settings/demo/components/pydantic_form.py
tgzr/contextual_settings/demo/components/utils.py
tgzr/contextual_settings/demo/components/sortable/__init__.py
tgzr/contextual_settings/demo/components/sortable/sortable_column.js
tgzr/contextual_settings/demo/components/sortable/sortable_column.py
tgzr/contextual_settings/demo/pages/README.md
tgzr/contextual_settings/demo/pages/__init__.py
tgzr/contextual_settings/demo/pages/examples/__init__.py
tgzr/contextual_settings/demo/pages/examples/app_config.py
tgzr/contextual_settings/demo/pages/examples/cg_asset_task.py
tgzr/contextual_settings/demo/pages/examples/items_and_collections.py
tgzr/contextual_settings/demo/pages/examples/startpage/__init__.py
tgzr_contextual_settings-0.100.dist-info/METADATA
tgzr_contextual_settings-0.100.dist-info/WHEEL
tgzr_contextual_settings-0.100.dist-info/entry_points.txt
tgzr_contextual_settings-0.100.dist-info/licenses/LICENSE
tgzr_contextual_settings-0.100.dist-info/RECORD
