Metadata-Version: 2.4
Name: tgzr.contextual_settings
Version: 0.100
Summary: Manage your configuration data by stacking grouped edits.
Project-URL: Documentation, https://github.com/open-tgzr/tgzr.contextual_settings
Project-URL: Issues, https://github.com/open-tgzr/tgzr.contextual_settings/issues
Project-URL: Source, https://github.com/open-tgzr/tgzr.contextual_settings
Author-email: Dee <dee.sometech@gmail.com>
License-Expression: GPL-3.0-or-later
License-File: LICENSE
Classifier: Development Status :: 4 - Beta
Classifier: Programming Language :: Python
Classifier: Programming Language :: Python :: 3.12
Classifier: Programming Language :: Python :: Implementation :: CPython
Classifier: Programming Language :: Python :: Implementation :: PyPy
Requires-Python: >=3.9
Requires-Dist: pydantic>=2.11.7
Requires-Dist: rich>=14.2.0
Provides-Extra: demo
Requires-Dist: fastapi[standard]>=0.115.14; extra == 'demo'
Requires-Dist: nicegui>=2.20.0; extra == 'demo'
Requires-Dist: tgzr-nice; extra == 'demo'
Provides-Extra: jetstream
Requires-Dist: nats-py[nkeys]; extra == 'jetstream'
